pydags/__init__.py
pydags/cache.py
pydags/pipeline.py
pydags/serialization.py
pydags/stage.py
pydags-0.1.1.dist-info/LICENSE
pydags-0.1.1.dist-info/METADATA
pydags-0.1.1.dist-info/WHEEL
pydags-0.1.1.dist-info/top_level.txt
pydags-0.1.1.dist-info/RECORD
