Metadata-Version: 2.1
Name: pydags
Version: 0.1.1
Summary: A simple, lightweight, extensible DAG framework for Python
Home-page: https://github.com/DavidTorpey/pydags
Author: David Torpey
Author-email: torpey.david93@gmail.com
License: GPLv3
Project-URL: Bug Tracker, https://github.com/DavidTorpey/pydags/issues
Platform: UNKNOWN
Classifier: Programming Language :: Python :: 3
Requires-Python: >=3.6
Requires-Dist: cloudpickle (==1.6.0)
Requires-Dist: dill (==0.3.3)
Requires-Dist: diskcache (==5.2.1)
Requires-Dist: matplotlib (==3.3.3)
Requires-Dist: networkx (==2.5)
Requires-Dist: pydot (==1.4.2)
Requires-Dist: redis (==3.5.3)
